asnake/__init__.py
asnake/configurator.py
asnake/aspace/__init__.py
asnake/client/__init__.py
asnake/client/web_client.py
asnake/jsonmodel/__init__.py
asnake/logging/__init__.py
asnake/utils/__init__.py
tests/__init__.py
tests/common.py
tests/test_aspace.py
tests/test_config.py
tests/test_utils.py
tests/test_web_client.py
ArchivesSnake-0.10.1.dist-info/LICENSE.txt
ArchivesSnake-0.10.1.dist-info/METADATA
ArchivesSnake-0.10.1.dist-info/WHEEL
ArchivesSnake-0.10.1.dist-info/top_level.txt
ArchivesSnake-0.10.1.dist-info/RECORD
