Metadata-Version: 2.1
Name: ArchivesSnake
Version: 0.10.1
Summary: ArchivesSpace Client Library
Home-page: https://github.com/archivesspace-labs/ArchivesSnake
Author: ArchivesSnake Developer Group
Author-email: asnake.developers@gmail.com
Classifier: Development Status :: 3 - Alpha
Classifier: Programming Language :: Python :: 3
Classifier: Intended Audience :: Other Audience
Classifier: License :: OSI Approved :: Apache Software License
Requires-Python: ~=3.4
License-File: LICENSE.txt
Requires-Dist: attrs
Requires-Dist: boltons
Requires-Dist: pyyaml
Requires-Dist: rapidfuzz
Requires-Dist: requests
Requires-Dist: structlog
Requires-Dist: more_itertools
